{ "locations" :
	[
		{
			"name"   : "Owen Smith",
			"lat"    : 49.2738005,
			"lon"    : -122.6713065,
			"marker" : "developer"
		},
		{
			"name"   : "Terrace, BC (CYXT)",
			"lat"    : 54.46639,
			"lon"    : -128.5797005,
			"marker" : "enhancedAirport"
		},
		{
			"name"   : "Vancouver, BC (CYVR)",
			"lat"    : 49.1943914,
			"lon"    : -123.1802675,
			"marker" : "enhancedAirport"
		},
		{
			"name"   : "108 Mile, BC (CZML)",
			"lat"    : 51.742496,
			"lon"    : -121.336269,
			"marker" : "enhancedAirport"
		},
		{
			"name"   : "Blue River, BC (CYCP)",
			"lat"    : 52.1231251,
			"lon"    : -119.2919151,
			"marker" : "favoriteAirport"
		},
		{
			"name"   : "Stewart, BC (CZST)",
			"lat"    : 55.9334474,
			"lon"    : -129.9834702,
			"marker" : "favoriteAirport"
		},
		{
			"name"   : "Vancouver, BC",
			"lat"    : 49.281020,
			"lon"    : -123.124123,
			"marker" : "enhancedScenery"
		},
		{
			"name"   : "Toronto, ON",
			"lat"    : 43.6425,
			"lon"    : -79.387222,
			"marker" : "enhancedScenery"
		},
		{
			"name"   : "Prince Rupert, BC",
			"lat"    : 54.294288,
			"lon"    : -130.357246,
			"marker" : "enhancedScenery"
		},
		{
			"name"   : "Alert, NU",
			"lat"    : 82.499176, 
			"lon"    : -62.350633,
			"marker" : "enhancedScenery"
		},
		{
			"name"   : "Cambridge Bay, NU",
			"lat"    : 69.116107, 
			"lon"    : -105.119769,
			"marker" : "enhancedScenery"
		},
		{
			"name"   : "Bear Mountain, BC",
			"lat"    : 55.699453, 
			"lon"    : -120.428009,
			"marker" : "windFarm"
		},
		{
			"name"   : "Eye of the Wind, BC",
			"lat"    : 49.387373, 
			"lon"    : -123.073912,
			"marker" : "windFarm"
		},
		{
			"name"   : "Dokie Ridge, BC",
			"lat"    : 55.805140, 
			"lon"    : -122.265472,
			"marker" : "windFarm"
		},
		{
			"name"   : "Quality Wind, BC",
			"lat"    : 55.190726, 
			"lon"    : -120.853043,
			"marker" : "windFarm"
		},
		{
			"name"   : "Cape Scott, BC",
			"lat"    : 50.776636, 
			"lon"    : -128.008232,
			"marker" : "windFarm"
		},
		{
			"name"   : "Meikle Wind, BC",
			"lat"    : 55.278626, 
			"lon"    : -121.469994,
			"marker" : "windFarm"
		},
		{
			"name"   : "St. Joseph Wind Farm, MAN",
			"lat"    : 49.143276, 
			"lon"    : -97.389853,
			"marker" : "windFarm"
		},
		{
			"name"   : "Baie-des-Sables Wind Farm, QUE",
			"lat"    : 48.702854, 
			"lon"    : -67.875566,
			"marker" : "windFarm"
		},
		{
			"name"   : "Jardin d'Eole Wind Farm, QUE",
			"lat"    : 48.731627, 
			"lon"    : -67.650118,
			"marker" : "windFarm"
		},
		{
			"name"   : "Le Nordais (Mantane), QUE",
			"lat"    : 48.778503, 
			"lon"    : -67.584521,
			"marker" : "windFarm"
		},
		{
			"name"   : "Le Nordais (Cap-Chat), QUE",
			"lat"    : 49.063431, 
			"lon"    : -66.755901,
			"marker" : "windFarm"
		},
		{
			"name"   : "Amaranth Wind, ONT",
			"lat"    : 44.108542, 
			"lon"    : -80.302677,
			"marker" : "windFarm"
		},
		{
			"name"   : "North Cape Wind, PEI",
			"lat"    : 47.048612, 
			"lon"    : -63.998399,
			"marker" : "windFarm"
		},
		{
			"name"   : "Norway Wind, PEI",
			"lat"    : 47.010439, 
			"lon"    : -64.024513,
			"marker" : "windFarm"
		},
		{
			"name"   : "WEICan R&D Wind Farm, PEI",
			"lat"    : 47.035635, 
			"lon"    : -64.013248,
			"marker" : "windFarm"
		},
		{
			"name"   : "West Cape Wind, PEI",
			"lat"    : 46.68358856, 
			"lon"    : -64.38595744,
			"marker" : "windFarm"
		},
		{
			"name"   : "Summerside Wind, PEI",
			"lat"    : 46.436032, 
			"lon"    : -63.799153,
			"marker" : "windFarm"
		},
		{
			"name"   : "Hermanville/Clearspring Wind, PEI",
			"lat"    : 46.452594, 
			"lon"    : -62.304002,
			"marker" : "windFarm"
		},
		{
			"name"   : "Eastern Kings Wind, PEI",
			"lat"    : 46.455578, 
			"lon"    : -62.047369,
			"marker" : "windFarm"
		}
    ]
}

